Metadata-Version: 2.1
Name: ig-profile
Version: 1.0
Summary: A simple package to extract the profile picture of a instagram user.
Home-page: https://github.com/debdutgoswami/instagram-profile-picture
Author: Debdut Goswami
Author-email: debdutgoswami@gmail.com
License: UNKNOWN
Download-URL: https://github.com/debdutgoswami/instagram-profile-picture/archive/v1.0.tar.gz
Keywords: INSTAGRAM,PROFILE,PICTURE
Platform: UNKNOWN
Classifier: Programming Language :: Python :: 3
Classifier: License :: OSI Approved :: MIT License
Classifier: Operating System :: OS Independent
Requires-Python: >=3.7
